routor/__init__.py
routor/__main__.py
routor/api/__init__.py
routor/api/config.py
routor/api/main.py
routor/api/models.py
routor/cli.py
routor/engine.py
routor/exceptions.py
routor/models.py
routor/py.typed
routor/utils/__init__.py
routor/utils/click.py
routor/utils/core.py
routor/utils/debug.py
routor/utils/graph.py
routor/weights.py
routor-0.7.1.dist-info/entry_points.txt
routor-0.7.1.dist-info/LICENSE
routor-0.7.1.dist-info/WHEEL
routor-0.7.1.dist-info/METADATA
routor-0.7.1.dist-info/RECORD
