Metadata-Version: 2.1
Name: routor
Version: 0.7.1
Summary: Simple osm routing engine.
Home-page: https://github.com/escaped/routor
License: BSD-3-Clause
Author: Alexander Frenzel
Author-email: alex@relatedworks.com
Requires-Python: >=3.6.1,<4.0
Classifier: Development Status :: 4 - Beta
Classifier: Environment :: Web Environment
Classifier: Intended Audience :: Developers
Classifier: License :: OSI Approved :: BSD License
Classifier: Operating System :: OS Independent
Classifier: Programming Language :: Python
Classifier: Programming Language :: Python :: 3
Classifier: Programming Language :: Python :: 3.10
Classifier: Programming Language :: Python :: 3.6
Classifier: Programming Language :: Python :: 3.7
Classifier: Programming Language :: Python :: 3.8
Classifier: Programming Language :: Python :: 3.9
Classifier: Topic :: Software Development :: Libraries :: Python Modules
Classifier: Typing :: Typed
Requires-Dist: click
Requires-Dist: fastapi
Requires-Dist: more-itertools (>8.0.0)
Requires-Dist: networkx (>2.5)
Requires-Dist: networkx-astar-path (>=1.0.1)
Requires-Dist: osmnx (>1.1.0)
Requires-Dist: pydantic (>1.5.0)
Requires-Dist: python-dotenv (>0.15.0)
Requires-Dist: scikit-learn
Requires-Dist: uvicorn
Project-URL: Documentation, https://github.com/escaped/routor/blob/master/README.md
Project-URL: Repository, https://github.com/escaped/routor
